{
  "name": "Minnie Moss",
  "age": 31,
  "address": {
    "street": "Emsoz Loop",
    "city": "Pimelpa",
    "state": "WV",
    "zip": "25443"
  },
  "contact": {
    "phone": "(719) 858-1470",
    "servicePhone": "800929845"
  },
  "birthday": "1998-04-28T08:04:45.937Z",
  "ip": "41.18.17.80",
  "foo": "bar",
  "profile": {
    "about": "Ifanarpek nuhorit wukov dewko degupak icilagug lahemled fan di nev zokjo vodtat wu ilan. Lib zepmuwpaz anupume iwo odreke wacnonir zasa duj fuamuho uvgedpu jid pe. Buur sokis gizte kesi nagon bihbadga ophapoj goc higijeb enu evokice simtac civas ruhzob de todip. Tehno wefeki hez wiharajos up zijkaj mel amotih vachavje kapud zum bun. Cahuoz mena sekojcam ziic vizam amaor kecho bakritcug koshib um cancup cof wewpe oj julka gonep.",
    "bio": "Wubure feeji uzo ejvajli fepef hu epi runillac viros foc ve vago. Zir iwaul deh cinguju val zud uk lo kedihreg sudjevwo fohza encur purges bomomeno uhisa wizzof. Idiazka habpeume fulmak luiweuba netnadne of fadakniv puvhu roc be faw juw ri sev baptogub vecdabez imabatu sitdal."
  },
  "apiKey": "495cd16698b07e0f385935d69bdf9afa0cea62f070544eb9010994386a3cdb3f",
  "currency": {
    "code": "COP",
    "name": "Colombia Peso"
  }
}