{
  "name": "Effie Lamb",
  "age": 53,
  "address": {
    "street": "Saura Mill",
    "city": "Kofpejhe",
    "state": "NH",
    "zip": "14693"
  },
  "contact": {
    "phone": "(802) 798-9896",
    "servicePhone": "800234173"
  },
  "birthday": "1962-10-30T06:00:04.923Z",
  "ip": "139.29.50.134",
  "foo": "bar",
  "profile": {
    "about": "Kab umuhuvug murkije hecfopru jihcet wenenugu di inowi hadbassow jineha ajuazsu wa redbe cucogma los cokvecuh. Goclohjig tuohisu jah simomaga be id ow gofo efdeno cejehve bisfa piidpu suhewo ar puce mumhib. Itre zoturi siuleob daugu latas owivertuh tewadig adibon jom judfetmav fom lege mabji ruviwe pozmak nilbopkaw usa.",
    "bio": "Uparuzit wu foseksaz robo jenauro naakifep idce tiguija en goomaogi ke padrosus do sineca. Wois tuobmat ra dam ucolejta huzamisu gijuhgu mek deoljo aczovzis ponhal cu pemvi me fevbe. Fapaje go van woc bofwah zudab vebmok ugo fo ojlubu tabuf peumsar dewekme faejke gu. Hinipov giwehaoc il he vimlahsep up seebe igowion tinuz fevju fe zormo heskof. Zakpir siti afcauho murkor oh cezka ikekepa ceg iwitosi um cu pej ithizpo bigippu fefufuz jiuseun cemu adedeeta."
  },
  "apiKey": "bd65047934f5e70cddf4c9951894888b573c43b974a059af6dd3ece720f2de06",
  "currency": {
    "code": "STD",
    "name": "São Tomé and Príncipe Dobra"
  }
}