{
  "name": "Timothy Gordon",
  "age": 50,
  "address": {
    "street": "Ojijus Terrace",
    "city": "Tettumwuh",
    "state": "CT",
    "zip": "73483"
  },
  "contact": {
    "phone": "(484) 494-8628",
    "servicePhone": "800485343"
  },
  "birthday": "1965-07-15T03:31:42.292Z",
  "ip": "114.191.139.91",
  "foo": "bar",
  "profile": {
    "about": "Etoirtur ukevetjam amu ledo wugsik meugza mowugih jeab kectavsis wovsip ka taco. Utku or irazul elli bipuzu pezkotok ra tamkaid tubunuc emza agcubsi kel izozoswa mosube. Sopipog sabgupnah mebhip bejpazraf nudec zeoro ron lumdudco alcusu urowut kam rupnonov ped ibop fule wihobule. Elwud asevaja evfo sifsobo ipjeg ede nabih co fupdu dah muk maju bum. Afi batinra oscawkof inoroza gimali sejhe netkapdo ahitog afa gip ur gi hoforo zapji rina. Pepefu ikbedmo mot rififu didouni wajo dimgamof efizofo wej ehu ajice biji difog. Jarauv tufa fe tuvdi womesih kaodem zosgutat sun woeve lopbo olagat fafjovod ur laoj we uh wan vura.",
    "bio": "Cashej ces runanebeh cufhup vas su bialosec purow ron ojhulido epuwifmez natteuma hef os. Du vocufcum va wobudigo rocjim eda inohu zubdubom ku li uzo ehi. Gowtiz nezpa zidwic zesfizuh fagwodsa afrol waf josor egjoru cemo dorfeg zuki fid se atusod ijne. Keoj ibi apievuir can duj hedfiwjit caku rez uvoeg cutpa pesu ci on ameamkuw goig hek. Wobwoide ubrok acevi agaherris or uno bino iwugodufi gazufo ibgepli da redgaler gi can jen. Zu sipnugza cevrovjoh wiwdefo ofolircik kakil jo di mivgo kohgis popa fohsetduk cebic. Uwefehmaw titojebi ab biwo etpilumo vup nubze hoccus isu zabtek an wov ed ni ubwut nu."
  },
  "apiKey": "8f754edd7a9798518213607f221ea221e6bd4c69896ab4a0dc084ece849f2364",
  "currency": {
    "code": "TWD",
    "name": "Taiwan New Dollar"
  }
}