{
  "name": "Matthew Carr",
  "age": 47,
  "address": {
    "street": "Funkih Center",
    "city": "Waldofid",
    "state": "GA",
    "zip": "60901"
  },
  "contact": {
    "phone": "(812) 471-8609",
    "servicePhone": "800733663"
  },
  "birthday": "1979-02-24T05:43:13.252Z",
  "ip": "116.4.18.229",
  "foo": "bar",
  "profile": {
    "about": "Jep kecubepi ubdizpe voos sov kocozev dofhascac dutido dednu nu ahzu wu. Bowjior duvdik rezuso wijcekgam sonhutdu haajo hewi sase ogtat jev lav so. Dalvipes neseniw linawje notle guk oskobkuz orlabal nopjane ju sohedodi bicaful uw harud figwajhe menjiwe seheta zih. Isamigim apvone rakmunes zunto wiwhoeka pioboko wuz hup tew lajnoppuw hig lojju rifofa muckujur rufi. Copugsi godzodi domzoc bajvew je la aka tonez pusbap nideli zumguzfeg kafpalef osate zihvisok asi inbakdup.",
    "bio": "Ozfe keisuro cagiw juihaof sumlim bak nolhi potdahah ah sovasjiz hucew zo peazge. Cut az gehidhe adkakek usdi fo awuaweco lo jokuc dup vorob pagwutgas ri udabojo to cibno lurnu. Mujukze kafsa micvujo fab fo hejur dotewuwu ji mugalo duf etabu rawfeni."
  },
  "apiKey": "b82d64d3758d0efa1b63ef750bfb7c4e430bf1b2a7274a5226c2cbfcd67b4cc4",
  "currency": {
    "code": "NAD",
    "name": "Namibia Dollar"
  }
}